{"__symbolic":"module","version":1,"metadata":{"LabelComponent":{"__symbolic":"class","decorators":[{"__symbolic":"call","expression":{"__symbolic":"reference","module":"@angular/core","name":"Component"},"arguments":[{"selector":"vcl-label","templateUrl":"label.component.html","host":{"[class.vclFormControlLabel]":"true","[class]":"labelClass"}}]}],"members":{"label":[{"__symbolic":"property","decorators":[{"__symbolic":"call","expression":{"__symbolic":"reference","module":"@angular/core","name":"Input"},"arguments":["label"]}]}],"subLabel":[{"__symbolic":"property","decorators":[{"__symbolic":"call","expression":{"__symbolic":"reference","module":"@angular/core","name":"Input"},"arguments":["subLabel"]}]}],"type":[{"__symbolic":"property","decorators":[{"__symbolic":"call","expression":{"__symbolic":"reference","module":"@angular/core","name":"Input"},"arguments":["type"]}]}],"requiredIndicatorCharacter":[{"__symbolic":"property","decorators":[{"__symbolic":"call","expression":{"__symbolic":"reference","module":"@angular/core","name":"Input"},"arguments":["requiredIndicatorCharacter"]}]}],"required":[{"__symbolic":"property","decorators":[{"__symbolic":"call","expression":{"__symbolic":"reference","module":"@angular/core","name":"Input"},"arguments":["required"]}]}],"for":[{"__symbolic":"property","decorators":[{"__symbolic":"call","expression":{"__symbolic":"reference","module":"@angular/core","name":"Input"},"arguments":["for"]}]}],"__ctor__":[{"__symbolic":"constructor"}],"ngOnInit":[{"__symbolic":"method"}],"ucfirst":[{"__symbolic":"method"}]}}}}